filefox/__init__.py
filefox/py.typed
filefox/text.py
filefox-0.7.0.dist-info/METADATA
filefox-0.7.0.dist-info/WHEEL
filefox-0.7.0.dist-info/RECORD
