Metadata-Version: 2.3
Name: filefox
Version: 0.7.0
Summary: Add your description here
Author-email: Yevgnen Koh <wherejoystarts@gmail.com>
Requires-Python: >=3.10
Requires-Dist: pytoml>=0.1.21
